rio/__init__.py
rio/__main__.py
rio/_compat.py
rio/app.py
rio/core.py
rio/manage.py
rio/setup.py
rio/signals.py
rio/tasks.py
rio/blueprints/__init__.py
rio/blueprints/api_1.py
rio/blueprints/dashboard.py
rio/blueprints/health.py
rio/blueprints/event/__init__.py
rio/blueprints/event/controllers.py
rio/blueprints/event/core.py
rio/blueprints/event/utils.py
rio/blueprints/event/views.py
rio/commands/__init__.py
rio/commands/runworker.py
rio/commands/syncproject.py
rio/exts/__init__.py
rio/exts/base.py
rio/exts/flask_cache.py
rio/exts/flask_redis_cluster.py
rio/graph/__init__.py
rio/graph/base.py
rio/graph/directory.py
rio/graph/errors.py
rio/graph/extension.py
rio/graph/sqlalchemy.py
rio/migrations/README
rio/migrations/__init__.py
rio/migrations/alembic.ini
rio/migrations/env.py
rio/migrations/script.py.mako
rio/migrations/versions/23416032b1cf_add_service.py
rio/migrations/versions/4cf90c101d82_init.py
rio/migrations/versions/__init__.py
rio/models/__init__.py
rio/models/action.py
rio/models/project.py
rio/models/sender.py
rio/models/service.py
rio/models/user.py
rio/models/utils.py
rio/models/webhook.py
rio/plugins/__init__.py
rio/plugins/environ/__init__.py
rio/plugins/environ/models.py
rio/settings/__init__.py
rio/settings/default.py
rio/settings/dev.py
rio/settings/test.py
rio/utils/__init__.py
rio/utils/http.py
rio/utils/slugify.py
rio/utils/template.py
rio/utils/token.py
rio/utils/user.py
rio-0.3.2.dist-info/DESCRIPTION.rst
rio-0.3.2.dist-info/METADATA
rio-0.3.2.dist-info/RECORD
rio-0.3.2.dist-info/WHEEL
rio-0.3.2.dist-info/entry_points.txt
rio-0.3.2.dist-info/metadata.json
rio-0.3.2.dist-info/top_level.txt
