Metadata-Version: 2.0
Name: rio
Version: 0.3.2
Summary: RESTful event dispatcher based on celery.
Home-page: https://github.com/soasme/rio
Author: Ju Lin
Author-email: soasme@gmail.com
License: MIT
Keywords: rio
Platform: UNKNOWN
Classifier: Development Status :: 2 - Pre-Alpha
Classifier: Intended Audience :: Developers
Classifier: License :: OSI Approved :: ISC License (ISCL)
Classifier: Natural Language :: English
Classifier: Programming Language :: Python :: 2
Classifier: Programming Language :: Python :: 2.6
Classifier: Programming Language :: Python :: 2.7
Classifier: Programming Language :: Python :: 3
Classifier: Programming Language :: Python :: 3.3
Classifier: Programming Language :: Python :: 3.4
Classifier: Programming Language :: Python :: 3.5
Requires-Dist: Flask-Celery-Helper (==1.1.0)
Requires-Dist: MySQL-python (==1.2.5)
Requires-Dist: awesome-slugify (==1.6.5)
Requires-Dist: blinker (==1.4)
Requires-Dist: celery (==3.1.23)
Requires-Dist: flask (==0.10.1)
Requires-Dist: flask-migrate (==1.8.0)
Requires-Dist: flask-sqlalchemy (==2.1)
Requires-Dist: flask-user (==0.6.8)
Requires-Dist: raven (==5.12.0)
Requires-Dist: rb (==1.4)
Requires-Dist: redis (==2.10.5)
Requires-Dist: requests (==2.9.1)
Requires-Dist: simplejson (==3.8.2)
